e2e/__init__.py
e2e/conftest.py
e2e/pages.py
e2e/test_add_row.py
e2e/test_array_columns.py
e2e/test_choices.py
e2e/test_codegen.py
e2e/test_constraints.py
e2e/test_csv_download.py
e2e/test_date_time_columns.py
e2e/test_file_upload.py
e2e/test_forms.py
e2e/test_logout.py
e2e/test_match.py
e2e/test_null_columns.py
e2e/test_operator.py
e2e/test_sort_columns.py
piccolo_admin/__init__.py
piccolo_admin/endpoints.py
piccolo_admin/piccolo_app.py
piccolo_admin/py.typed
piccolo_admin/sandbox.py
piccolo_admin/version.py
piccolo_admin/version.txt
piccolo_admin/dist/index.html
piccolo_admin/dist/assets/index-C-GxPbuk.css
piccolo_admin/dist/assets/index-CJwCX2Wu.js
piccolo_admin/example/__init__.py
piccolo_admin/example/app.py
piccolo_admin/example/data.py
piccolo_admin/example/tables.py
piccolo_admin/example/forms/__init__.py
piccolo_admin/example/forms/calculator.py
piccolo_admin/example/forms/csv.py
piccolo_admin/example/forms/email.py
piccolo_admin/example/forms/image.py
piccolo_admin/example/forms/nullable.py
piccolo_admin/example/forms/files/movie_listings.jpg
piccolo_admin/piccolo_migrations/__init__.py
piccolo_admin/translations/__init__.py
piccolo_admin/translations/data.py
piccolo_admin/translations/models.py
piccolo_admin-1.12.0.dist-info/licenses/LICENSE
piccolo_admin-1.12.0.dist-info/METADATA
piccolo_admin-1.12.0.dist-info/WHEEL
piccolo_admin-1.12.0.dist-info/entry_points.txt
piccolo_admin-1.12.0.dist-info/top_level.txt
piccolo_admin-1.12.0.dist-info/RECORD
