Metadata-Version: 2.4
Name: piccolo_admin
Version: 1.12.0
Summary: A powerful and modern admin interface / CMS, powered by Piccolo and ASGI.
Home-page: https://github.com/piccolo-orm/piccolo_admin
Author: Daniel Townsend
Author-email: dan@dantownsend.co.uk
License: MIT
Classifier: License :: OSI Approved :: MIT License
Classifier: Programming Language :: Python
Classifier: Programming Language :: Python :: 3
Classifier: Programming Language :: Python :: 3.9
Classifier: Programming Language :: Python :: 3.10
Classifier: Programming Language :: Python :: 3.11
Classifier: Programming Language :: Python :: 3.12
Classifier: Programming Language :: Python :: 3.13
Classifier: Programming Language :: Python :: Implementation :: CPython
Classifier: Topic :: Database :: Front-Ends
Classifier: Topic :: Internet :: WWW/HTTP :: Dynamic Content :: Content Management System
Requires-Python: >=3.9.0
License-File: LICENSE
Requires-Dist: piccolo>=1.7.0
Requires-Dist: piccolo_api>=1.5.2
Requires-Dist: uvicorn
Requires-Dist: aiofiles>=0.5.0
Requires-Dist: Hypercorn
Requires-Dist: targ>=0.1.9
Requires-Dist: fastapi>=0.100.0
Provides-Extra: faker
Requires-Dist: faker==13.*; extra == "faker"
Provides-Extra: s3
Requires-Dist: piccolo_api[s3]; extra == "s3"
Provides-Extra: all
Requires-Dist: faker==13.*; extra == "all"
Requires-Dist: piccolo_api[s3]; extra == "all"
Dynamic: author
Dynamic: author-email
Dynamic: classifier
Dynamic: description
Dynamic: description-content-type
Dynamic: home-page
Dynamic: license
Dynamic: license-file
Dynamic: provides-extra
Dynamic: requires-dist
Dynamic: requires-python
Dynamic: summary
